ijroipytiff/__init__.py
ijroipytiff/ij_ovalroi.py
ijroipytiff/ij_roi.py
ijroipytiff/ijpython_decoder.py
ijroipytiff/ijpython_encoder.py
ijroipytiff/wand.py
ijroipytiff-0.0.6.dist-info/METADATA
ijroipytiff-0.0.6.dist-info/WHEEL
ijroipytiff-0.0.6.dist-info/top_level.txt
ijroipytiff-0.0.6.dist-info/RECORD
