Metadata-Version: 2.1
Name: ijroipytiff
Version: 0.0.6
Summary: Python library for reading and writing ImageJ (or Fiji) ROI and storing them in IJ Tiff format, compatible with Tifffile library.
Home-page: https://github.com/dwaithe/ijpython_roi
Author: Dominic Waithe
Author-email: dominic_waithe@hotmail.com
License: UNKNOWN
Project-URL: Bug Tracker, https://github.com/dwaithe/ijpython_roi/issues
Platform: UNKNOWN
Classifier: Programming Language :: Python :: 3
Classifier: License :: OSI Approved :: MIT License
Classifier: Operating System :: OS Independent
Requires-Python: >=3.6
